zblocker.py
zblocker-1.0.2.dist-info/METADATA
zblocker-1.0.2.dist-info/RECORD
zblocker-1.0.2.dist-info/WHEEL
zblocker-1.0.2.dist-info/top_level.txt
